{
  "type_id": 15747,
  "name": "Republic Fleet 5MN Microwarpdrive",
  "description": "Massive boost to speed for a very short time. The thrust that boosts the ship, and the corresponding maximum velocity bonus, are limited by the mass of the ship that uses this module. The sheer amount of energy needed to power this system means that it must permanently reserve a fraction of the capacitor output just to maintain the integrity of its warp containment field, and when activated it substantially increases the ship's EM footprint.\n\nPenalty: Max capacitor reduced.\n\nNote: Usually fit on Frigates and Destroyers.",
  "volume": 10.0,
  "repackaged_volume": null,
  "capacity": null,
  "mass": null,
  "category_name": "Module",
  "group_name": "Propulsion Module",
  "attributes": [
    {
      "attribute_name": "capacitorNeed",
      "value": 45.0,
      "categoryID": 5,
      "display_name": "Activation Cost",
      "unit_name": "GJ"
    },
    {
      "attribute_name": "hp",
      "value": 40.0,
      "categoryID": 4,
      "display_name": "Structure Hitpoints",
      "unit_name": "HP"
    },
    {
      "attribute_name": "speedFactor",
      "value": 512.0,
      "categoryID": 28,
      "display_name": "Maximum Velocity Bonus",
      "unit_name": "%"
    },
    {
      "attribute_name": "power",
      "value": 17.0,
      "categoryID": 1,
      "display_name": "Powergrid Usage",
      "unit_name": "MW"
    },
    {
      "attribute_name": "cpu",
      "value": 25.0,
      "categoryID": 1,
      "display_name": "CPU usage",
      "unit_name": "tf"
    },
    {
      "attribute_name": "duration",
      "value": 10000.0,
      "categoryID": 7,
      "display_name": "Activation time / duration",
      "unit_name": "s"
    },
    {
      "attribute_name": "capacitorCapacityMultiplier",
      "value": 0.9,
      "categoryID": 5,
      "display_name": "Capacitor Capacity Bonus",
      "unit_name": "%"
    },
    {
      "attribute_name": "requiredSkill1",
      "value": 3454.0,
      "categoryID": 8,
      "display_name": "Primary Skill required",
      "unit_name": "typeID"
    },
    {
      "attribute_name": "requiredSkill1Level",
      "value": 1.0,
      "categoryID": 8,
      "display_name": null,
      "unit_name": null
    },
    {
      "attribute_name": "techLevel",
      "value": 1.0,
      "categoryID": 7,
      "display_name": "Tech Level",
      "unit_name": "Level"
    },
    {
      "attribute_name": "signatureRadiusBonus",
      "value": 450.0,
      "categoryID": 21,
      "display_name": "Signature Radius Modifier",
      "unit_name": "%"
    },
    {
      "attribute_name": "speedBoostFactor",
      "value": 1500000.0,
      "categoryID": 7,
      "display_name": "Thrust",
      "unit_name": "N"
    },
    {
      "attribute_name": "metaLevelOld",
      "value": 8.0,
      "categoryID": 7,
      "display_name": "Meta Level",
      "unit_name": "Level"
    },
    {
      "attribute_name": "moduleReactivationDelay",
      "value": 0.0,
      "categoryID": 7,
      "display_name": "Reactivation Delay",
      "unit_name": "s"
    },
    {
      "attribute_name": "maxGroupActive",
      "value": 1.0,
      "categoryID": 9,
      "display_name": null,
      "unit_name": null
    },
    {
      "attribute_name": "massAddition",
      "value": 500000.0,
      "categoryID": 7,
      "display_name": "Mass Addition",
      "unit_name": "kg"
    },
    {
      "attribute_name": "deadspaceUnsafe",
      "value": 1.0,
      "categoryID": 9,
      "display_name": null,
      "unit_name": null
    },
    {
      "attribute_name": "heatAbsorbtionRateModifier",
      "value": 0.04,
      "categoryID": 52,
      "display_name": null,
      "unit_name": null
    },
    {
      "attribute_name": "heatDamage",
      "value": 19.0,
      "categoryID": 52,
      "display_name": "Heat Damage",
      "unit_name": "HP"
    },
    {
      "attribute_name": "requiredThermoDynamicsSkill",
      "value": 1.0,
      "categoryID": 7,
      "display_name": "Required Thermodynamics Level",
      "unit_name": "Level"
    },
    {
      "attribute_name": "overloadSpeedFactorBonus",
      "value": 50.0,
      "categoryID": 7,
      "display_name": "Overload Speed Bonus",
      "unit_name": "%"
    },
    {
      "attribute_name": "metaGroupID",
      "value": 4.0,
      "categoryID": 0,
      "display_name": null,
      "unit_name": null
    }
  ],
  "traits": []
}