{
  "type_id": 37883,
  "name": "95th Interstellar Mindclash Championship Tickets",
  "description": "VIP tickets detailed with gold leaf and blue tigers, along with the embossed portrait of defending Interstellar Mindclash Champion Joelyn Donalokos. These tickets are now used, but once granted access to the 95th Interstellar Mindclash Championships, which was hosted at the Grand Teigjon Resort & Casino in October YC117.",
  "volume": 0.01,
  "repackaged_volume": null,
  "capacity": null,
  "mass": null,
  "category_name": "Special Edition Assets",
  "group_name": "Special Edition Commodities",
  "attributes": [],
  "traits": []
}