{
  "type_id": 25233,
  "name": "Corporation Contracting",
  "description": "You are familiar with the intricacies of formalizing contracts between your corporation and other entities. \n\nFor each level of this skill the number of concurrent corporation/alliance contracts you make on behalf of your corporation is increased by 10 up to a maximum of 60. \n\nThis skill has no effect on contracts you make personally.\n\nThere is no limit on the number of contracts a corporation can assign to itself.\n\nCorporations have a hard limit of 500 outstanding public contracts.",
  "volume": 0.01,
  "repackaged_volume": null,
  "capacity": null,
  "mass": null,
  "category_name": "Skill",
  "group_name": "Trade",
  "attributes": [
    {
      "attribute_name": "primaryAttribute",
      "value": 164.0,
      "categoryID": 7,
      "display_name": "Primary attribute",
      "unit_name": "attributeID"
    },
    {
      "attribute_name": "secondaryAttribute",
      "value": 168.0,
      "categoryID": 7,
      "display_name": "Secondary attribute",
      "unit_name": "attributeID"
    },
    {
      "attribute_name": "requiredSkill1",
      "value": 25235.0,
      "categoryID": 8,
      "display_name": "Primary Skill required",
      "unit_name": "typeID"
    },
    {
      "attribute_name": "skillTimeConstant",
      "value": 3.0,
      "categoryID": 7,
      "display_name": "Training time multiplier",
      "unit_name": "x"
    },
    {
      "attribute_name": "requiredSkill1Level",
      "value": 4.0,
      "categoryID": 8,
      "display_name": null,
      "unit_name": null
    },
    {
      "attribute_name": "skillLevel",
      "value": 0.0,
      "categoryID": 7,
      "display_name": "Level",
      "unit_name": null
    },
    {
      "attribute_name": "canNotBeTrainedOnTrial",
      "value": 1.0,
      "categoryID": 9,
      "display_name": null,
      "unit_name": null
    }
  ],
  "traits": []
}