{
  "type_id": 30586,
  "name": "Malfunctioning Power Cores",
  "description": "Taken from amongst countless other ruined devices that cluttered the Sleeper facility once housing them, these ancient Sleeper power cores are still intact, yet extremely defective. Unlocking the technological secrets behind them would be a difficult task in their current state. Only those researchers who are skilled in reverse engineering would have a chance, and even then, not a great one.",
  "volume": 10.0,
  "repackaged_volume": null,
  "capacity": null,
  "mass": null,
  "category_name": "Ancient Relics",
  "group_name": "Sleeper Engineering Relics",
  "attributes": [
    {
      "attribute_name": "industryBlueprintRank",
      "value": 2.0,
      "categoryID": 7,
      "display_name": null,
      "unit_name": null
    }
  ],
  "traits": []
}