{
  "type_id": 33040,
  "name": "NEO YC 114: Oxygen Isonopes",
  "description": "One of twenty-seven different cards created for the first ever New Eden Open tournament of YC 114. While not the first ever capsuleer tournament it was the first of its kind to be sponsored by a private media organization and broadcast to a much larger audience. It was also set a new benchmark for prizes in a capsuleer tournament.\n\nThe New Eden Open broke the tradition of previous capsuleer tournaments by allowing teams to form at will, without the need to be bound to the same alliance.\n\nThis card represents the following team and sponsor:\n<font color=\"0xff00CC00\">Team Name:</font> Oxygen Isonopes\n<font color=\"0xff00CC00\">Sponsor Name:</font> No team sponsor.\n\n<font size=\"14\" color=\"0xff0099FF\"><b>Team Captain:</b></font>\n<url=showinfo:1377//751832309>Warr Akini</url>\n\n<font size=\"14\" color=\"0xff0099FF\"><b>Team Members:</b></font>\n<url=showinfo:1377//821185360>BlackSabbath</url>\n<url=showinfo:1377//1399211800>Braygo Khallazar</url>\n<url=showinfo:1377//826128382>Diogenes Diaspora</url>\n<url=showinfo:1377//167352969>eC Cade</url>\n<url=showinfo:1377//1523206482>Firvain</url>\n<url=showinfo:1377//1760421798>FOl2TY8</url>\n<url=showinfo:1377//1469734517>Fyzick</url>\n<url=showinfo:1377//1091875696>Halosponge</url>\n<url=showinfo:1377//680120572>Jaroslav</url>\n<url=showinfo:1377//928536456>Jenya Lin</url>\n<url=showinfo:1377//90613965>Kyle Myr</url>\n<url=showinfo:1377//1136947120>Lasius</url>\n<url=showinfo:1377//435846426>Leykab</url>\n<url=showinfo:1377//1883470581>Liam Jacobs</url>\n<url=showinfo:1377//1853733254>Lord Regent</url>\n<url=showinfo:1377//1821356839>Masra lor</url>\n<url=showinfo:1377//958372469>Rehtom Lamina</url>\n<url=showinfo:1377//248529845>Teljkon Nugs</url>\n<url=showinfo:1377//1868446148>Tiberizzle</url>\n<url=showinfo:1377//376185646>Titmando</url>\n<url=showinfo:1377//564586053>Travis Wells</url>\n<url=showinfo:1377//916015256>Vena Saris</url>\n<url=showinfo:1377//858761439>Xolve</url>\n\n<i>Can you collect them all?</i>",
  "volume": 0.01,
  "repackaged_volume": null,
  "capacity": null,
  "mass": null,
  "category_name": "Special Edition Assets",
  "group_name": "Tournament Cards: New Eden Open YC 114",
  "attributes": [],
  "traits": []
}