{
  "type_id": 3697,
  "name": "硅酸盐玻璃",
  "description": "硅酸盐玻璃是一种普通的建筑材料，在新伊甸的宇宙中有着稳定的需求量，用于行星设施的建造或者经过强化后用于空间舰船。",
  "volume": 0.75,
  "repackaged_volume": null,
  "capacity": null,
  "mass": null,
  "category_name": "行星商品",
  "group_name": "加工过的资源物品 - 第二等级",
  "attributes": [
    {
      "attribute_name": "importTaxMultiplier",
      "value": 7200.0,
      "categoryID": 7,
      "display_name": null,
      "unit_name": "%"
    },
    {
      "attribute_name": "exportTaxMultiplier",
      "value": 7200.0,
      "categoryID": 7,
      "display_name": null,
      "unit_name": "%"
    }
  ],
  "traits": []
}