{
  "type_id": 17445,
  "name": "希莫非特（3级）",
  "description": "希莫非特有许多种颜色的变体。有趣的是，颜色越鲜艳的希莫非特，矿物含量就越高。辐射希莫非特含有的矿物比色彩黯淡的同种矿石高10%。希莫非特含有大量<a href=showinfo:38>超新星诺克石</a>，因此找到这种矿石总是美事一桩。它并非十分罕见，即使是采矿新手也可能与它不期而遇。希莫非特含有一定数量的<a href=showinfo:37>同位聚合体</a>。大多数情况下，你可以在低安全等级星系找到它。",
  "volume": 3.0,
  "repackaged_volume": null,
  "capacity": null,
  "mass": 1e+35,
  "category_name": "小行星",
  "group_name": "希莫非特",
  "attributes": [
    {
      "attribute_name": "requiredSkill1",
      "value": 3386.0,
      "categoryID": 8,
      "display_name": "主技能需求",
      "unit_name": "类别ID"
    },
    {
      "attribute_name": "requiredSkill1Level",
      "value": 1.0,
      "categoryID": 8,
      "display_name": null,
      "unit_name": null
    },
    {
      "attribute_name": "reprocessingSkillType",
      "value": 60378.0,
      "categoryID": 7,
      "display_name": "回收再生技能",
      "unit_name": "类别ID"
    },
    {
      "attribute_name": "asteroidRadiusGrowthFactor",
      "value": 0.5,
      "categoryID": 31,
      "display_name": "小行星半径系数",
      "unit_name": null
    },
    {
      "attribute_name": "asteroidRadiusUnitSize",
      "value": 600.0,
      "categoryID": 31,
      "display_name": "小行星单位半径",
      "unit_name": "m"
    },
    {
      "attribute_name": "stasisWebifierResistance",
      "value": 0.0,
      "categoryID": 36,
      "display_name": "停滞缠绕抗性",
      "unit_name": "%"
    },
    {
      "attribute_name": "asteroidMetaLevel",
      "value": 3.0,
      "categoryID": 7,
      "display_name": null,
      "unit_name": null
    },
    {
      "attribute_name": "oreBasicType",
      "value": 1231.0,
      "categoryID": 7,
      "display_name": null,
      "unit_name": "类别ID"
    }
  ],
  "traits": []
}