{
  "type_id": 62389,
  "name": "高密度藤黄丝胶溶质",
  "description": "丝胶溶质是在大型小行星和卫星内部高压环境中形成的晶体，常用于电子和武器制造业，也被用于生产高级战斗增效剂。磷胶溶质仅分布在少数地区，例如低安星系和零安星系的气云中。   ( copy )",
  "volume": 1.0,
  "repackaged_volume": null,
  "capacity": null,
  "mass": null,
  "category_name": "天体",
  "group_name": "高密度气云",
  "attributes": [
    {
      "attribute_name": "ignoreMiningWaste",
      "value": 1.0,
      "categoryID": 51,
      "display_name": null,
      "unit_name": null
    },
    {
      "attribute_name": "ignoreMiningCrits",
      "value": 1.0,
      "categoryID": 51,
      "display_name": null,
      "unit_name": null
    }
  ],
  "traits": []
}