{
  "type_id": 12224,
  "name": "Capital Remote Capacitor Transmitter II Blueprint",
  "description": "",
  "volume": 0.01,
  "repackaged_volume": null,
  "capacity": null,
  "mass": null,
  "category_name": "Blueprint",
  "group_name": "Remote Capacitor Transmitter Blueprint",
  "attributes": [
    {
      "attribute_name": "techLevel",
      "value": 2.0,
      "categoryID": 7,
      "display_name": "Tech Level",
      "unit_name": "Level"
    },
    {
      "attribute_name": "industryBlueprintRank",
      "value": 312.0,
      "categoryID": 7,
      "display_name": "",
      "unit_name": ""
    }
  ],
  "traits": []
}